django_simulated_inlines/__init__.py
django_simulated_inlines/admin.py
django_simulated_inlines/migrations/__init__.py
django_simulated_inlines/static/django_simulated_inlines/js/simulated_inlines.js
django_simulated_inlines/templates/admin/django_simulated_inlines/change_form.html
django_simulated_inlines/templates/admin/django_simulated_inlines/list.html
django_simulated_inlines-0.1.dist-info/LICENSE
django_simulated_inlines-0.1.dist-info/METADATA
django_simulated_inlines-0.1.dist-info/WHEEL
django_simulated_inlines-0.1.dist-info/top_level.txt
django_simulated_inlines-0.1.dist-info/RECORD
