Metadata-Version: 2.1
Name: django-simulated-inlines
Version: 0.1
Summary: A Django app to allow for readonly admin inlines without relationship to the base model
Home-page: https://gitlab.com/pmcoelho/django_simulated_inlines
Author: Pedro Maia Coelho
Author-email: pmcoelho@protonmail.com
License: MIT
Platform: UNKNOWN
Classifier: Environment :: Web Environment
Classifier: Framework :: Django
Classifier: Intended Audience :: Developers
Classifier: Programming Language :: Python :: 3
